LICENSE
MANIFEST.in
README.rst
buildout.cfg
requirements.txt
setup.py
version.txt
bob/__init__.py
bob.db.iostar.egg-info/PKG-INFO
bob.db.iostar.egg-info/SOURCES.txt
bob.db.iostar.egg-info/dependency_links.txt
bob.db.iostar.egg-info/entry_points.txt
bob.db.iostar.egg-info/not-zip-safe
bob.db.iostar.egg-info/requires.txt
bob.db.iostar.egg-info/top_level.txt
bob/db/__init__.py
bob/db/iostar/__init__.py
bob/db/iostar/checkfiles.py
bob/db/iostar/create.py
bob/db/iostar/driver.py
bob/db/iostar/iostar_db_default_od.json
bob/db/iostar/iostar_db_default_vessel.json
bob/db/iostar/iostar_test_od.csv
bob/db/iostar/iostar_test_vessel.csv
bob/db/iostar/iostar_train_od.csv
bob/db/iostar/iostar_train_vessel.csv
bob/db/iostar/models.py
bob/db/iostar/query.py
bob/db/iostar/test.py
doc/guide.rst
doc/index.rst
doc/links.rst
doc/py_api.rst
doc/img/bob-128x128.png
doc/img/bob-favicon.ico
doc/img/bob-logo.png